{
    "tasks": [
        {
            "id": "93f5",
            "userId": "32c4880f-d626-4bca-b5d9-baf7a7735b9c",
            "title": "Sobreviver por 1 dias",
            "description": "Vc consegue!",
            "term": "2024-06-29",
            "priority": "alta",
            "complete": false
        },
        {
            "id": "93f6",
            "userId": "32c4880f-d626-4bca-b5d9-baf7a7735b9c",
            "title": "Sobreviver por 2 dias",
            "description": "Vc nao consegue!",
            "term": "2024-07-03",
            "priority": "alta",
            "complete": false
        },
        {
            "id": "93f7",
            "userId": "32c4880f-d626-4bca-b5d9-baf7a7735b9c",
            "title": "Sobreviver por 3 dias",
            "description": "Vc nunca consegue!",
            "term": "2024-07-04",
            "priority": "alta",
            "complete": false
        }
    ]
}